masaki39_zotero_mcp-0.1.1.dist-info/licenses/LICENSE
zotero_mcp/__init__.py
zotero_mcp/__main__.py
masaki39_zotero_mcp-0.1.1.dist-info/METADATA
masaki39_zotero_mcp-0.1.1.dist-info/WHEEL
masaki39_zotero_mcp-0.1.1.dist-info/entry_points.txt
masaki39_zotero_mcp-0.1.1.dist-info/top_level.txt
masaki39_zotero_mcp-0.1.1.dist-info/RECORD
