Metadata-Version: 2.4
Name: masaki39-zotero-mcp
Version: 0.1.1
Summary: MCP server for Zotero integration - search, retrieve, and extract PDF text from your Zotero library
Author-email: masaki39 <masaki39@example.com>
License-Expression: MIT
Project-URL: Homepage, https://github.com/masaki39/zotero-mcp
Project-URL: Repository, https://github.com/masaki39/zotero-mcp
Project-URL: Issues, https://github.com/masaki39/zotero-mcp/issues
Keywords: zotero,mcp,model-context-protocol,pdf,research,bibliography
Classifier: Development Status :: 3 - Alpha
Classifier: Intended Audience :: Developers
Classifier: Intended Audience :: Science/Research
Classifier: Programming Language :: Python :: 3
Classifier: Programming Language :: Python :: 3.12
Classifier: Topic :: Scientific/Engineering
Classifier: Topic :: Software Development :: Libraries :: Python Modules
Requires-Python: >=3.12
License-File: LICENSE
Requires-Dist: httpx>=0.28.1
Requires-Dist: mcp[cli]>=1.7.1
Requires-Dist: PyPDF2>=3.0.0
Dynamic: license-file
